[{"id":"20z8630s1il","title":"2023/9/28 14:46:40","block":{"name":"MyBlock","title":"测试区块","inject":[],"state":{"value":{"type":"JSExpression","value":"''"}},"lifeCycles":{},"methods":{},"computed":{},"watch":[],"css":"","props":[{"name":"title","type":["String"],"required":false,"default":{"type":"JSExpression","value":"'默认参数标题文本'"}}],"emits":["submit"],"slots":["default"],"transform":{},"dataSources":{},"__VTJ_BLOCK__":true,"id":"1bh5ci0vpnp","children":[{"props":{"header":{"type":"JSExpression","value":"this.$props.title"},"footer":{"flex":true}},"name":"XPanel","from":"@vtj/ui","id":"1e4ussdvwj4","invisible":false,"children":[{"props":{"height":"300px","style":{"width":"100%"}},"children":[{"name":"ElCarouselItem","props":{"style":{"width":"100%"}},"children":[{"name":"component","props":{"is":"img","style":{"width":"100%","height":"300px"},"src":"https://fuss10.elemecdn.com/e/5d/4a731a90594a4af544c0c25941171jpeg.jpeg"},"id":"n22888sorj","from":"","invisible":false,"children":"","directives":[],"events":{}}],"directives":[{"id":"1igtlzxfr6o","name":"vFor","value":{"type":"JSExpression","value":"3"}}],"id":"b55hwi2k4f","from":"","invisible":false,"events":{}}],"name":"ElCarousel","from":"element-plus","id":"1yt8rgxia1r","invisible":false,"directives":[],"events":{}},{"name":"ElDivider","children":[],"from":"element-plus","id":"2afinzu5cpe","invisible":false,"props":{},"directives":[],"events":{}},{"props":{"fit":true,"auto":true},"name":"XContainer","from":"@vtj/ui","id":"d0i2pfsh68","invisible":false,"children":[{"children":"插槽默认内容","name":"slot","from":"","id":"21yo9g6rjlx","invisible":false,"props":{},"directives":[],"events":{}}],"directives":[],"events":{}},{"name":"ElInput","from":"element-plus","id":"1emkugz21w2","invisible":false,"slot":{"name":"footer","params":[]},"children":"","props":{"placeholder":"请输入事件参数文本"},"directives":[{"id":"2aj29x8uvml","name":"vModel","arg":"modelValue","value":{"type":"JSExpression","value":"this.state.value"}}],"events":{}},{"name":"ElButton","children":"测试触发事件","props":{"type":"primary"},"from":"element-plus","id":"ix6mw4vvx6","invisible":false,"slot":{"name":"footer","params":[]},"directives":[],"events":{"click":{"handler":{"type":"JSFunction","value":"() => {\r\n    this.$emit('submit', this.state.value)\r\n}"},"modifiers":{}}}}],"directives":[],"events":{}}]}},{"id":"25ltt3pnkzt","title":"2023/9/28 14:44:20","block":{"name":"MyBlock","title":"测试区块","inject":[],"state":{"value":{"type":"JSExpression","value":"''"}},"lifeCycles":{},"methods":{},"computed":{},"watch":[],"css":"","props":[{"name":"title","type":["String"],"required":false,"default":{"type":"JSExpression","value":"'默认参数标题文本'"}}],"emits":["submit"],"slots":[],"transform":{},"dataSources":{},"__VTJ_BLOCK__":true,"id":"1bh5ci0vpnp","children":[{"props":{"header":{"type":"JSExpression","value":"this.$props.title"},"footer":{"flex":true}},"name":"XPanel","from":"@vtj/ui","id":"1e4ussdvwj4","invisible":false,"children":[{"props":{"height":"300px","style":{"width":"100%"}},"children":[{"name":"ElCarouselItem","props":{"style":{"width":"100%"}},"children":[{"name":"component","props":{"is":"img","style":{"width":"100%","height":"300px"},"src":"https://fuss10.elemecdn.com/e/5d/4a731a90594a4af544c0c25941171jpeg.jpeg"},"id":"n22888sorj","from":"","invisible":false,"children":"","directives":[],"events":{}}],"directives":[{"id":"1igtlzxfr6o","name":"vFor","value":{"type":"JSExpression","value":"3"}}],"id":"b55hwi2k4f","from":"","invisible":false,"events":{}}],"name":"ElCarousel","from":"element-plus","id":"1yt8rgxia1r","invisible":false,"directives":[],"events":{}},{"name":"ElDivider","children":[],"from":"element-plus","id":"2afinzu5cpe","invisible":false,"props":{},"directives":[],"events":{}},{"props":{"fit":true,"auto":true},"name":"XContainer","from":"@vtj/ui","id":"d0i2pfsh68","invisible":false,"children":[{"children":"插槽默认内容","name":"slot","from":"","id":"21yo9g6rjlx","invisible":false,"props":{},"directives":[],"events":{}}],"directives":[],"events":{}},{"name":"ElInput","from":"element-plus","id":"1emkugz21w2","invisible":false,"slot":{"name":"footer","params":[]},"children":"","props":{"placeholder":"请输入事件参数文本"},"directives":[{"id":"2aj29x8uvml","name":"vModel","arg":"modelValue","value":{"type":"JSExpression","value":"this.state.value"}}],"events":{}},{"name":"ElButton","children":"测试触发事件","props":{"type":"primary"},"from":"element-plus","id":"ix6mw4vvx6","invisible":false,"slot":{"name":"footer","params":[]},"directives":[],"events":{"click":{"handler":{"type":"JSFunction","value":"() => {\r\n    this.$emit('submit', this.state.value)\r\n}"},"modifiers":{}}}}],"directives":[],"events":{}}]}},{"id":"156ackgto1w","title":"2023/9/28 14:44:20","block":{"name":"MyBlock","title":"测试区块","inject":[],"state":{"value":{"type":"JSExpression","value":"''"}},"lifeCycles":{},"methods":{},"computed":{},"watch":[],"css":"","props":[{"name":"title","type":["String"],"required":false,"default":{"type":"JSExpression","value":"'默认参数标题文本'"}}],"emits":["submit"],"slots":[],"transform":{},"dataSources":{},"__VTJ_BLOCK__":true,"id":"1bh5ci0vpnp","children":[{"props":{"header":{"type":"JSExpression","value":"this.$props.title"},"footer":{"flex":true}},"name":"XPanel","from":"@vtj/ui","id":"1e4ussdvwj4","invisible":false,"children":[{"props":{"height":"300px","style":{"width":"100%"}},"children":[{"name":"ElCarouselItem","props":{"style":{"width":"100%"}},"children":[{"name":"component","props":{"is":"img","style":{"width":"100%","height":"300px"},"src":"https://fuss10.elemecdn.com/e/5d/4a731a90594a4af544c0c25941171jpeg.jpeg"},"id":"n22888sorj","from":"","invisible":false,"children":"","directives":[],"events":{}}],"directives":[{"id":"1igtlzxfr6o","name":"vFor","value":{"type":"JSExpression","value":"3"}}],"id":"b55hwi2k4f","from":"","invisible":false,"events":{}}],"name":"ElCarousel","from":"element-plus","id":"1yt8rgxia1r","invisible":false,"directives":[],"events":{}},{"name":"ElDivider","children":[],"from":"element-plus","id":"2afinzu5cpe","invisible":false,"props":{},"directives":[],"events":{}},{"props":{"fit":true,"auto":true},"name":"XContainer","from":"@vtj/ui","id":"d0i2pfsh68","invisible":false,"children":"插槽默认内容","directives":[],"events":{}},{"name":"ElInput","from":"element-plus","id":"1emkugz21w2","invisible":false,"slot":{"name":"footer","params":[]},"children":"","props":{"placeholder":"请输入事件参数文本"},"directives":[{"id":"2aj29x8uvml","name":"vModel","arg":"modelValue","value":{"type":"JSExpression","value":"this.state.value"}}],"events":{}},{"name":"ElButton","children":"测试触发事件","props":{"type":"primary"},"from":"element-plus","id":"ix6mw4vvx6","invisible":false,"slot":{"name":"footer","params":[]},"directives":[],"events":{"click":{"handler":{"type":"JSFunction","value":"() => {\r\n    this.$emit('submit', this.state.value)\r\n}"},"modifiers":{}}}}],"directives":[],"events":{}}]}},{"id":"1l82o8bgtuj","title":"2023/9/28 14:44:13","block":{"name":"MyBlock","title":"测试区块","inject":[],"state":{"value":{"type":"JSExpression","value":"''"}},"lifeCycles":{},"methods":{},"computed":{},"watch":[],"css":"","props":[{"name":"title","type":["String"],"required":false,"default":{"type":"JSExpression","value":"'默认参数标题文本'"}}],"emits":["submit"],"slots":[],"transform":{},"dataSources":{},"__VTJ_BLOCK__":true,"id":"1bh5ci0vpnp","children":[{"props":{"header":{"type":"JSExpression","value":"this.$props.title"},"footer":{"flex":true}},"name":"XPanel","from":"@vtj/ui","id":"1e4ussdvwj4","invisible":false,"children":[{"props":{"height":"300px","style":{"width":"100%"}},"children":[{"name":"ElCarouselItem","props":{"style":{"width":"100%"}},"children":[{"name":"component","props":{"is":"img","style":{"width":"100%","height":"300px"},"src":"https://fuss10.elemecdn.com/e/5d/4a731a90594a4af544c0c25941171jpeg.jpeg"},"id":"n22888sorj","from":"","invisible":false,"children":"","directives":[],"events":{}}],"directives":[{"id":"1igtlzxfr6o","name":"vFor","value":{"type":"JSExpression","value":"3"}}],"id":"b55hwi2k4f","from":"","invisible":false,"events":{}}],"name":"ElCarousel","from":"element-plus","id":"1yt8rgxia1r","invisible":false,"directives":[],"events":{}},{"name":"ElDivider","children":[],"from":"element-plus","id":"2afinzu5cpe","invisible":false,"props":{},"directives":[],"events":{}},{"children":"插槽默认内容","name":"slot","from":"","id":"21yo9g6rjlx","invisible":false,"props":{},"directives":[],"events":{}},{"props":{"fit":true,"auto":true},"name":"XContainer","from":"@vtj/ui","id":"d0i2pfsh68","invisible":false,"children":"插槽默认内容","directives":[],"events":{}},{"name":"ElInput","from":"element-plus","id":"1emkugz21w2","invisible":false,"slot":{"name":"footer","params":[]},"children":"","props":{"placeholder":"请输入事件参数文本"},"directives":[{"id":"2aj29x8uvml","name":"vModel","arg":"modelValue","value":{"type":"JSExpression","value":"this.state.value"}}],"events":{}},{"name":"ElButton","children":"测试触发事件","props":{"type":"primary"},"from":"element-plus","id":"ix6mw4vvx6","invisible":false,"slot":{"name":"footer","params":[]},"directives":[],"events":{"click":{"handler":{"type":"JSFunction","value":"() => {\r\n    this.$emit('submit', this.state.value)\r\n}"},"modifiers":{}}}}],"directives":[],"events":{}}]}},{"id":"sdh4t9t9ey","title":"2023/9/28 14:43:52","block":{"name":"MyBlock","title":"测试区块","inject":[],"state":{"value":{"type":"JSExpression","value":"''"}},"lifeCycles":{},"methods":{},"computed":{},"watch":[],"css":"","props":[{"name":"title","type":["String"],"required":false,"default":{"type":"JSExpression","value":"'默认参数标题文本'"}}],"emits":["submit"],"slots":[],"transform":{},"dataSources":{},"__VTJ_BLOCK__":true,"id":"1bh5ci0vpnp","children":[{"props":{"header":{"type":"JSExpression","value":"this.$props.title"},"footer":{"flex":true}},"name":"XPanel","from":"@vtj/ui","id":"1e4ussdvwj4","invisible":false,"children":[{"props":{"height":"300px","style":{"width":"100%"}},"children":[{"name":"ElCarouselItem","props":{"style":{"width":"100%"}},"children":[{"name":"component","props":{"is":"img","style":{"width":"100%","height":"300px"},"src":"https://fuss10.elemecdn.com/e/5d/4a731a90594a4af544c0c25941171jpeg.jpeg"},"id":"n22888sorj","from":"","invisible":false,"children":"","directives":[],"events":{}}],"directives":[{"id":"1igtlzxfr6o","name":"vFor","value":{"type":"JSExpression","value":"3"}}],"id":"b55hwi2k4f","from":"","invisible":false,"events":{}}],"name":"ElCarousel","from":"element-plus","id":"1yt8rgxia1r","invisible":false,"directives":[],"events":{}},{"name":"ElDivider","children":[],"from":"element-plus","id":"2afinzu5cpe","invisible":false,"props":{},"directives":[],"events":{}},{"props":{"fit":true,"auto":true},"name":"XContainer","from":"@vtj/ui","id":"d0i2pfsh68","invisible":false,"children":"插槽默认内容","directives":[],"events":{}},{"name":"ElInput","from":"element-plus","id":"1emkugz21w2","invisible":false,"slot":{"name":"footer","params":[]},"children":"","props":{"placeholder":"请输入事件参数文本"},"directives":[{"id":"2aj29x8uvml","name":"vModel","arg":"modelValue","value":{"type":"JSExpression","value":"this.state.value"}}],"events":{}},{"name":"ElButton","children":"测试触发事件","props":{"type":"primary"},"from":"element-plus","id":"ix6mw4vvx6","invisible":false,"slot":{"name":"footer","params":[]},"directives":[],"events":{"click":{"handler":{"type":"JSFunction","value":"() => {\r\n    this.$emit('submit', this.state.value)\r\n}"},"modifiers":{}}}}],"directives":[],"events":{}}]}},{"id":"1ex7oafqql1","title":"2023/9/28 14:43:15","block":{"name":"MyBlock","title":"测试区块","inject":[],"state":{"value":{"type":"JSExpression","value":"''"}},"lifeCycles":{},"methods":{},"computed":{},"watch":[],"css":"","props":[{"name":"title","type":["String"],"required":false,"default":{"type":"JSExpression","value":"'默认参数标题文本'"}}],"emits":["submit"],"slots":[],"transform":{},"dataSources":{},"__VTJ_BLOCK__":true,"id":"1bh5ci0vpnp","children":[{"props":{"header":{"type":"JSExpression","value":"this.$props.title"},"footer":{"flex":true}},"name":"XPanel","from":"@vtj/ui","id":"1e4ussdvwj4","invisible":false,"children":[{"props":{"height":"300px","style":{"width":"100%"}},"children":[{"name":"ElCarouselItem","props":{"style":{"width":"100%"}},"children":[{"name":"component","props":{"is":"img","style":{"width":"100%","height":"300px"},"src":"https://fuss10.elemecdn.com/e/5d/4a731a90594a4af544c0c25941171jpeg.jpeg"},"id":"n22888sorj","from":"","invisible":false,"children":"","directives":[],"events":{}}],"directives":[{"id":"1igtlzxfr6o","name":"vFor","value":{"type":"JSExpression","value":"3"}}],"id":"b55hwi2k4f","from":"","invisible":false,"events":{}}],"name":"ElCarousel","from":"element-plus","id":"1yt8rgxia1r","invisible":false,"directives":[],"events":{}},{"name":"ElDivider","children":[],"from":"element-plus","id":"2afinzu5cpe","invisible":false,"props":{},"directives":[],"events":{}},{"props":{"fit":true,"auto":true},"name":"XContainer","from":"@vtj/ui","id":"d0i2pfsh68","invisible":false,"children":"","directives":[],"events":{}},{"name":"ElInput","from":"element-plus","id":"1emkugz21w2","invisible":false,"slot":{"name":"footer","params":[]},"children":"","props":{"placeholder":"请输入事件参数文本"},"directives":[{"id":"2aj29x8uvml","name":"vModel","arg":"modelValue","value":{"type":"JSExpression","value":"this.state.value"}}],"events":{}},{"name":"ElButton","children":"测试触发事件","props":{"type":"primary"},"from":"element-plus","id":"ix6mw4vvx6","invisible":false,"slot":{"name":"footer","params":[]},"directives":[],"events":{"click":{"handler":{"type":"JSFunction","value":"() => {\r\n    this.$emit('submit', this.state.value)\r\n}"},"modifiers":{}}}}],"directives":[],"events":{}}]}},{"id":"v16l3mlhxo","title":"2023/9/28 14:43:15","block":{"name":"MyBlock","title":"测试区块","inject":[],"state":{"value":{"type":"JSExpression","value":"''"}},"lifeCycles":{},"methods":{},"computed":{},"watch":[],"css":"","props":[{"name":"title","type":["String"],"required":false,"default":{"type":"JSExpression","value":"'默认参数标题文本'"}}],"emits":["submit"],"slots":[],"transform":{},"dataSources":{},"__VTJ_BLOCK__":true,"id":"1bh5ci0vpnp","children":[{"props":{"header":{"type":"JSExpression","value":"this.$props.title"},"footer":{"flex":true}},"name":"XPanel","from":"@vtj/ui","id":"1e4ussdvwj4","invisible":false,"children":[{"props":{"height":"300px","style":{"width":"100%"}},"children":[{"name":"ElCarouselItem","props":{"style":{"width":"100%"}},"children":[{"name":"component","props":{"is":"img","style":{"width":"100%","height":"300px"},"src":"https://fuss10.elemecdn.com/e/5d/4a731a90594a4af544c0c25941171jpeg.jpeg"},"id":"n22888sorj","from":"","invisible":false,"children":"","directives":[],"events":{}}],"directives":[{"id":"1igtlzxfr6o","name":"vFor","value":{"type":"JSExpression","value":"3"}}],"id":"b55hwi2k4f","from":"","invisible":false,"events":{}}],"name":"ElCarousel","from":"element-plus","id":"1yt8rgxia1r","invisible":false,"directives":[],"events":{}},{"name":"ElDivider","children":[],"from":"element-plus","id":"2afinzu5cpe","invisible":false,"props":{},"directives":[],"events":{}},{"name":"ElInput","from":"element-plus","id":"1emkugz21w2","invisible":false,"slot":{"name":"footer","params":[]},"children":"","props":{"placeholder":"请输入事件参数文本"},"directives":[{"id":"2aj29x8uvml","name":"vModel","arg":"modelValue","value":{"type":"JSExpression","value":"this.state.value"}}],"events":{}},{"name":"ElButton","children":"测试触发事件","props":{"type":"primary"},"from":"element-plus","id":"ix6mw4vvx6","invisible":false,"slot":{"name":"footer","params":[]},"directives":[],"events":{"click":{"handler":{"type":"JSFunction","value":"() => {\r\n    this.$emit('submit', this.state.value)\r\n}"},"modifiers":{}}}}],"directives":[],"events":{}}]}},{"id":"1lf5w3r1i44","title":"2023/9/28 14:43:05","block":{"name":"MyBlock","title":"测试区块","inject":[],"state":{"value":{"type":"JSExpression","value":"''"}},"lifeCycles":{},"methods":{},"computed":{},"watch":[],"css":"","props":[{"name":"title","type":["String"],"required":false,"default":{"type":"JSExpression","value":"'默认参数标题文本'"}}],"emits":["submit"],"slots":[],"transform":{},"dataSources":{},"__VTJ_BLOCK__":true,"id":"1bh5ci0vpnp","children":[{"props":{"header":{"type":"JSExpression","value":"this.$props.title"},"footer":{"flex":true}},"name":"XPanel","from":"@vtj/ui","id":"1e4ussdvwj4","invisible":false,"children":[{"props":{"height":"300px","style":{"width":"100%"}},"children":[{"name":"ElCarouselItem","props":{"style":{"width":"100%"}},"children":[{"name":"component","props":{"is":"img","style":{"width":"100%","height":"300px"},"src":"https://fuss10.elemecdn.com/e/5d/4a731a90594a4af544c0c25941171jpeg.jpeg"},"id":"n22888sorj","from":"","invisible":false,"children":"","directives":[],"events":{}}],"directives":[{"id":"1igtlzxfr6o","name":"vFor","value":{"type":"JSExpression","value":"3"}}],"id":"b55hwi2k4f","from":"","invisible":false,"events":{}}],"name":"ElCarousel","from":"element-plus","id":"1yt8rgxia1r","invisible":false,"directives":[],"events":{}},{"name":"ElDivider","children":[{"props":{"fit":true,"auto":true},"name":"XContainer","from":"@vtj/ui","id":"d0i2pfsh68","invisible":false,"children":"","directives":[],"events":{}}],"from":"element-plus","id":"2afinzu5cpe","invisible":false,"props":{},"directives":[],"events":{}},{"name":"ElInput","from":"element-plus","id":"1emkugz21w2","invisible":false,"slot":{"name":"footer","params":[]},"children":"","props":{"placeholder":"请输入事件参数文本"},"directives":[{"id":"2aj29x8uvml","name":"vModel","arg":"modelValue","value":{"type":"JSExpression","value":"this.state.value"}}],"events":{}},{"name":"ElButton","children":"测试触发事件","props":{"type":"primary"},"from":"element-plus","id":"ix6mw4vvx6","invisible":false,"slot":{"name":"footer","params":[]},"directives":[],"events":{"click":{"handler":{"type":"JSFunction","value":"() => {\r\n    this.$emit('submit', this.state.value)\r\n}"},"modifiers":{}}}}],"directives":[],"events":{}}]}},{"id":"156ackgr49z","title":"2023/9/28 14:42:21","block":{"name":"MyBlock","title":"测试区块","inject":[],"state":{"value":{"type":"JSExpression","value":"''"}},"lifeCycles":{},"methods":{},"computed":{},"watch":[],"css":"","props":[{"name":"title","type":["String"],"required":false,"default":{"type":"JSExpression","value":"'默认参数标题文本'"}}],"emits":["submit"],"slots":[],"transform":{},"dataSources":{},"__VTJ_BLOCK__":true,"id":"1bh5ci0vpnp","children":[{"props":{"header":{"type":"JSExpression","value":"this.$props.title"},"footer":{"flex":true}},"name":"XPanel","from":"@vtj/ui","id":"1e4ussdvwj4","invisible":false,"children":[{"props":{"height":"300px","style":{"width":"100%"}},"children":[{"name":"ElCarouselItem","props":{"style":{"width":"100%"}},"children":[{"name":"component","props":{"is":"img","style":{"width":"100%","height":"300px"},"src":"https://fuss10.elemecdn.com/e/5d/4a731a90594a4af544c0c25941171jpeg.jpeg"},"id":"n22888sorj","from":"","invisible":false,"children":"","directives":[],"events":{}}],"directives":[{"id":"1igtlzxfr6o","name":"vFor","value":{"type":"JSExpression","value":"3"}}],"id":"b55hwi2k4f","from":"","invisible":false,"events":{}}],"name":"ElCarousel","from":"element-plus","id":"1yt8rgxia1r","invisible":false,"directives":[],"events":{}},{"name":"ElDivider","children":"分割线","from":"element-plus","id":"2afinzu5cpe","invisible":false,"props":{},"directives":[],"events":{}},{"name":"ElInput","from":"element-plus","id":"1emkugz21w2","invisible":false,"slot":{"name":"footer","params":[]},"children":"","props":{"placeholder":"请输入事件参数文本"},"directives":[{"id":"2aj29x8uvml","name":"vModel","arg":"modelValue","value":{"type":"JSExpression","value":"this.state.value"}}],"events":{}},{"name":"ElButton","children":"测试触发事件","props":{"type":"primary"},"from":"element-plus","id":"ix6mw4vvx6","invisible":false,"slot":{"name":"footer","params":[]},"directives":[],"events":{"click":{"handler":{"type":"JSFunction","value":"() => {\r\n    this.$emit('submit', this.state.value)\r\n}"},"modifiers":{}}}}],"directives":[],"events":{}}]}},{"id":"1vgq1mve9gh","title":"2023/9/28 14:42:21","block":{"name":"MyBlock","title":"测试区块","inject":[],"state":{"value":{"type":"JSExpression","value":"''"}},"lifeCycles":{},"methods":{},"computed":{},"watch":[],"css":"","props":[{"name":"title","type":["String"],"required":false,"default":{"type":"JSExpression","value":"'默认参数标题文本'"}}],"emits":["submit"],"slots":[],"transform":{},"dataSources":{},"__VTJ_BLOCK__":true,"id":"1bh5ci0vpnp","children":[{"props":{"header":{"type":"JSExpression","value":"this.$props.title"},"footer":{"flex":true}},"name":"XPanel","from":"@vtj/ui","id":"1e4ussdvwj4","invisible":false,"children":[{"props":{"height":"300px","style":{"width":"100%"}},"children":[{"name":"ElCarouselItem","props":{"style":{"width":"100%"}},"children":[{"name":"component","props":{"is":"img","style":{"width":"100%","height":"300px"},"src":"https://fuss10.elemecdn.com/e/5d/4a731a90594a4af544c0c25941171jpeg.jpeg"},"id":"n22888sorj","from":"","invisible":false,"children":"","directives":[],"events":{}}],"directives":[{"id":"1igtlzxfr6o","name":"vFor","value":{"type":"JSExpression","value":"3"}}],"id":"b55hwi2k4f","from":"","invisible":false,"events":{}}],"name":"ElCarousel","from":"element-plus","id":"1yt8rgxia1r","invisible":false,"directives":[],"events":{}},{"name":"ElInput","from":"element-plus","id":"1emkugz21w2","invisible":false,"slot":{"name":"footer","params":[]},"children":"","props":{"placeholder":"请输入事件参数文本"},"directives":[{"id":"2aj29x8uvml","name":"vModel","arg":"modelValue","value":{"type":"JSExpression","value":"this.state.value"}}],"events":{}},{"name":"ElButton","children":"测试触发事件","props":{"type":"primary"},"from":"element-plus","id":"ix6mw4vvx6","invisible":false,"slot":{"name":"footer","params":[]},"directives":[],"events":{"click":{"handler":{"type":"JSFunction","value":"() => {\r\n    this.$emit('submit', this.state.value)\r\n}"},"modifiers":{}}}}],"directives":[],"events":{}}]}},{"id":"3gnyuweug6","title":"2023/9/28 14:42:03","block":{"name":"MyBlock","title":"测试区块","inject":[],"state":{"value":{"type":"JSExpression","value":"''"}},"lifeCycles":{},"methods":{},"computed":{},"watch":[],"css":"","props":[{"name":"title","type":["String"],"required":false,"default":{"type":"JSExpression","value":"'默认参数标题文本'"}}],"emits":["submit"],"slots":[],"transform":{},"dataSources":{},"__VTJ_BLOCK__":true,"id":"1bh5ci0vpnp","children":[{"props":{"header":{"type":"JSExpression","value":"this.$props.title"},"footer":{"flex":true}},"name":"XPanel","from":"@vtj/ui","id":"1e4ussdvwj4","invisible":false,"children":[{"props":{"height":"300px","style":{"width":"100%"}},"children":[{"name":"ElCarouselItem","props":{"style":{"width":"100%"}},"children":[{"name":"component","props":{"is":"img","style":{"width":"100%","height":"300px"},"src":"https://fuss10.elemecdn.com/e/5d/4a731a90594a4af544c0c25941171jpeg.jpeg"},"id":"n22888sorj","from":"","invisible":false,"children":"","directives":[],"events":{}}],"directives":[{"id":"1igtlzxfr6o","name":"vFor","value":{"type":"JSExpression","value":"3"}}],"id":"b55hwi2k4f","from":"","invisible":false,"events":{}}],"name":"ElCarousel","from":"element-plus","id":"1yt8rgxia1r","invisible":false,"directives":[],"events":{}},{"name":"ElInput","from":"element-plus","id":"1emkugz21w2","invisible":false,"slot":{"name":"footer","params":[]},"children":"","props":{"placeholder":"请输入事件参数文本"},"directives":[{"id":"2aj29x8uvml","name":"vModel","arg":"modelValue","value":{"type":"JSExpression","value":"this.state.value"}}],"events":{}},{"name":"ElButton","children":"测试触发事件","props":{"type":"primary"},"from":"element-plus","id":"ix6mw4vvx6","invisible":false,"slot":{"name":"footer","params":[]},"directives":[],"events":{"click":{"handler":{"type":"JSFunction","value":"() => {\r\n    this.$emit('submit', this.state.value)\r\n}"},"modifiers":{}}}}],"directives":[],"events":{}},{"name":"ElDivider","children":"分割线","from":"element-plus","id":"2afinzu5cpe","invisible":false,"props":{},"directives":[],"events":{}}]}},{"id":"kozlr1oucc","title":"2023/9/28 09:32:25","block":{"name":"MyBlock","title":"测试区块","inject":[],"state":{"value":{"type":"JSExpression","value":"''"}},"lifeCycles":{},"methods":{},"computed":{},"watch":[],"css":"","props":[{"name":"title","type":["String"],"required":false,"default":{"type":"JSExpression","value":"'默认参数标题文本'"}}],"emits":["submit"],"slots":[],"transform":{},"dataSources":{},"__VTJ_BLOCK__":true,"id":"1bh5ci0vpnp","children":[{"props":{"header":{"type":"JSExpression","value":"this.$props.title"},"footer":{"flex":true}},"name":"XPanel","from":"@vtj/ui","id":"1e4ussdvwj4","invisible":false,"children":[{"props":{"height":"300px","style":{"width":"100%"}},"children":[{"name":"ElCarouselItem","props":{"style":{"width":"100%"}},"children":[{"name":"component","props":{"is":"img","style":{"width":"100%","height":"300px"},"src":"https://fuss10.elemecdn.com/e/5d/4a731a90594a4af544c0c25941171jpeg.jpeg"},"id":"n22888sorj","from":"","invisible":false,"children":"","directives":[],"events":{}}],"directives":[{"id":"1igtlzxfr6o","name":"vFor","value":{"type":"JSExpression","value":"3"}}],"id":"b55hwi2k4f","from":"","invisible":false,"events":{}}],"name":"ElCarousel","from":"element-plus","id":"1yt8rgxia1r","invisible":false,"directives":[],"events":{}},{"name":"ElInput","from":"element-plus","id":"1emkugz21w2","invisible":false,"slot":{"name":"footer","params":[]},"children":"","props":{"placeholder":"请输入事件参数文本"},"directives":[{"id":"2aj29x8uvml","name":"vModel","arg":"modelValue","value":{"type":"JSExpression","value":"this.state.value"}}],"events":{}},{"name":"ElButton","children":"测试触发事件","props":{"type":"primary"},"from":"element-plus","id":"ix6mw4vvx6","invisible":false,"slot":{"name":"footer","params":[]},"directives":[],"events":{"click":{"handler":{"type":"JSFunction","value":"() => {\r\n    this.$emit('submit', this.state.value)\r\n}"},"modifiers":{}}}}],"directives":[],"events":{}}]}},{"id":"oxet0vecuv","title":"2023/9/28 09:31:51","block":{"name":"MyBlock","title":"测试区块","inject":[],"state":{"value":{"type":"JSExpression","value":"''"}},"lifeCycles":{},"methods":{},"computed":{},"watch":[],"css":"","props":[{"name":"title","type":["String"],"required":false,"default":{"type":"JSExpression","value":"'默认参数标题文本'"}}],"emits":["submit"],"slots":[],"transform":{},"dataSources":{},"__VTJ_BLOCK__":true,"id":"1bh5ci0vpnp","children":[{"props":{"header":{"type":"JSExpression","value":"this.$props.title"},"footer":{"flex":true}},"name":"XPanel","from":"@vtj/ui","id":"1e4ussdvwj4","invisible":false,"children":[{"props":{"height":"300px","style":{"width":"100%"}},"children":[{"name":"ElCarouselItem","props":{"style":{"width":"100%"}},"children":[{"name":"component","props":{"is":"img","style":{"width":"100%","height":"300px"},"src":"https://fuss10.elemecdn.com/e/5d/4a731a90594a4af544c0c25941171jpeg.jpeg"},"id":"n22888sorj","from":"","invisible":false,"children":"","directives":[],"events":{}}],"directives":[{"id":"1igtlzxfr6o","name":"vFor","value":{"type":"JSExpression","value":"3"}}],"id":"b55hwi2k4f","from":"","invisible":false,"events":{}}],"name":"ElCarousel","from":"element-plus","id":"1yt8rgxia1r","invisible":false,"directives":[],"events":{}},{"name":"ElInput","from":"element-plus","id":"1emkugz21w2","invisible":false,"slot":{"name":"footer","params":[]},"children":"","props":{"placeholder":"请输入事件参数文本"},"directives":[{"id":"2aj29x8uvml","name":"vModel","arg":"modelValue","value":{"type":"JSExpression","value":"this.state.value"}}],"events":{}},{"name":"ElButton","children":"测试触发事件","props":{"type":"primary"},"from":"element-plus","id":"ix6mw4vvx6","invisible":false,"slot":{"name":"footer","params":[]},"directives":[],"events":{}}],"directives":[],"events":{}}]}},{"id":"19lsrpezbza","title":"2023/9/28 09:31:10","block":{"name":"MyBlock","title":"测试区块","inject":[],"state":{"value":{"type":"JSExpression","value":"''"}},"lifeCycles":{},"methods":{},"computed":{},"watch":[],"css":"","props":[{"name":"title","type":["String"],"required":false,"default":{"type":"JSExpression","value":"'默认参数标题文本'"}}],"emits":["submit"],"slots":[],"transform":{},"dataSources":{},"__VTJ_BLOCK__":true,"id":"1bh5ci0vpnp","children":[{"props":{"header":{"type":"JSExpression","value":"this.$props.title"},"footer":{"flex":true}},"name":"XPanel","from":"@vtj/ui","id":"1e4ussdvwj4","invisible":false,"children":[{"props":{"height":"300px","style":{"width":"100%"}},"children":[{"name":"ElCarouselItem","props":{"style":{"width":"100%"}},"children":[{"name":"component","props":{"is":"img","style":{"width":"100%","height":"300px"},"src":"https://fuss10.elemecdn.com/e/5d/4a731a90594a4af544c0c25941171jpeg.jpeg"},"id":"n22888sorj","from":"","invisible":false,"children":"","directives":[],"events":{}}],"directives":[{"id":"1igtlzxfr6o","name":"vFor","value":{"type":"JSExpression","value":"3"}}],"id":"b55hwi2k4f","from":"","invisible":false,"events":{}}],"name":"ElCarousel","from":"element-plus","id":"1yt8rgxia1r","invisible":false,"directives":[],"events":{}},{"name":"ElInput","from":"element-plus","id":"1emkugz21w2","invisible":false,"slot":{"name":"footer","params":[]},"children":"","props":{"placeholder":"请输入事件参数文本"},"directives":[],"events":{}},{"name":"ElButton","children":"测试触发事件","props":{"type":"primary"},"from":"element-plus","id":"ix6mw4vvx6","invisible":false,"slot":{"name":"footer","params":[]},"directives":[],"events":{}}],"directives":[],"events":{}}]}},{"id":"ggkeh7uwbi","title":"2023/9/28 09:29:32","block":{"name":"MyBlock","title":"测试区块","inject":[],"state":{},"lifeCycles":{},"methods":{},"computed":{},"watch":[],"css":"","props":[{"name":"title","type":["String"],"required":false,"default":{"type":"JSExpression","value":"'默认参数标题文本'"}}],"emits":["submit"],"slots":[],"transform":{},"dataSources":{},"__VTJ_BLOCK__":true,"id":"1bh5ci0vpnp","children":[{"props":{"header":{"type":"JSExpression","value":"this.$props.title"},"footer":{"flex":true}},"name":"XPanel","from":"@vtj/ui","id":"1e4ussdvwj4","invisible":false,"children":[{"props":{"height":"300px","style":{"width":"100%"}},"children":[{"name":"ElCarouselItem","props":{"style":{"width":"100%"}},"children":[{"name":"component","props":{"is":"img","style":{"width":"100%","height":"300px"},"src":"https://fuss10.elemecdn.com/e/5d/4a731a90594a4af544c0c25941171jpeg.jpeg"},"id":"n22888sorj","from":"","invisible":false,"children":"","directives":[],"events":{}}],"directives":[{"id":"1igtlzxfr6o","name":"vFor","value":{"type":"JSExpression","value":"3"}}],"id":"b55hwi2k4f","from":"","invisible":false,"events":{}}],"name":"ElCarousel","from":"element-plus","id":"1yt8rgxia1r","invisible":false,"directives":[],"events":{}},{"name":"ElInput","from":"element-plus","id":"1emkugz21w2","invisible":false,"slot":{"name":"footer","params":[]},"children":"","props":{"placeholder":"请输入事件参数文本"},"directives":[],"events":{}},{"name":"ElButton","children":"测试触发事件","props":{"type":"primary"},"from":"element-plus","id":"ix6mw4vvx6","invisible":false,"slot":{"name":"footer","params":[]},"directives":[],"events":{}}],"directives":[],"events":{}}]}},{"id":"24879zd2uc8","title":"2023/9/28 09:28:52","block":{"name":"MyBlock","title":"测试区块","inject":[],"state":{},"lifeCycles":{},"methods":{},"computed":{},"watch":[],"css":"","props":[{"name":"title","type":["String"],"required":false,"default":{"type":"JSExpression","value":"'默认参数标题文本'"}}],"emits":["submit"],"slots":[],"transform":{},"dataSources":{},"__VTJ_BLOCK__":true,"id":"1bh5ci0vpnp","children":[{"props":{"header":{"type":"JSExpression","value":"this.$props.title"},"footer":{"flex":true}},"name":"XPanel","from":"@vtj/ui","id":"1e4ussdvwj4","invisible":false,"children":[{"props":{"height":"300px","style":{"width":"100%"}},"children":[{"name":"ElCarouselItem","props":{"style":{"width":"100%"}},"children":[{"name":"component","props":{"is":"img","style":{"width":"100%","height":"300px"},"src":"https://fuss10.elemecdn.com/e/5d/4a731a90594a4af544c0c25941171jpeg.jpeg"},"id":"n22888sorj","from":"","invisible":false,"children":"","directives":[],"events":{}}],"directives":[{"id":"1igtlzxfr6o","name":"vFor","value":{"type":"JSExpression","value":"3"}}],"id":"b55hwi2k4f","from":"","invisible":false,"events":{}}],"name":"ElCarousel","from":"element-plus","id":"1yt8rgxia1r","invisible":false,"directives":[],"events":{}},{"name":"ElInput","from":"element-plus","id":"1emkugz21w2","invisible":false,"slot":{"name":"footer","params":[]},"children":"","props":{},"directives":[],"events":{}},{"name":"ElButton","children":"测试触发事件","props":{"type":"primary"},"from":"element-plus","id":"ix6mw4vvx6","invisible":false,"slot":{"name":"footer","params":[]},"directives":[],"events":{}}],"directives":[],"events":{}}]}},{"id":"hu6xl94aeh","title":"2023/9/28 09:28:14","block":{"name":"MyBlock","title":"测试区块","inject":[],"state":{},"lifeCycles":{},"methods":{},"computed":{},"watch":[],"css":"","props":[{"name":"title","type":["String"],"required":false,"default":{"type":"JSExpression","value":"'默认参数标题文本'"}}],"emits":["submit"],"slots":[],"transform":{},"dataSources":{},"__VTJ_BLOCK__":true,"id":"1bh5ci0vpnp","children":[{"props":{"header":{"type":"JSExpression","value":"this.$props.title"}},"name":"XPanel","from":"@vtj/ui","id":"1e4ussdvwj4","invisible":false,"children":[{"props":{"height":"300px","style":{"width":"100%"}},"children":[{"name":"ElCarouselItem","props":{"style":{"width":"100%"}},"children":[{"name":"component","props":{"is":"img","style":{"width":"100%","height":"300px"},"src":"https://fuss10.elemecdn.com/e/5d/4a731a90594a4af544c0c25941171jpeg.jpeg"},"id":"n22888sorj","from":"","invisible":false,"children":"","directives":[],"events":{}}],"directives":[{"id":"1igtlzxfr6o","name":"vFor","value":{"type":"JSExpression","value":"3"}}],"id":"b55hwi2k4f","from":"","invisible":false,"events":{}}],"name":"ElCarousel","from":"element-plus","id":"1yt8rgxia1r","invisible":false,"directives":[],"events":{}},{"name":"ElInput","from":"element-plus","id":"1emkugz21w2","invisible":false,"slot":{"name":"footer","params":[]},"children":"","props":{},"directives":[],"events":{}},{"name":"ElButton","children":"测试触发事件","props":{"type":"primary"},"from":"element-plus","id":"ix6mw4vvx6","invisible":false,"slot":{"name":"footer","params":[]},"directives":[],"events":{}}],"directives":[],"events":{}}]}},{"id":"qp7rvrt2ud","title":"2023/9/28 09:28:14","block":{"name":"MyBlock","title":"测试区块","inject":[],"state":{},"lifeCycles":{},"methods":{},"computed":{},"watch":[],"css":"","props":[{"name":"title","type":["String"],"required":false,"default":{"type":"JSExpression","value":"'默认参数标题文本'"}}],"emits":["submit"],"slots":[],"transform":{},"dataSources":{},"__VTJ_BLOCK__":true,"id":"1bh5ci0vpnp","children":[{"props":{"header":{"type":"JSExpression","value":"this.$props.title"}},"name":"XPanel","from":"@vtj/ui","id":"1e4ussdvwj4","invisible":false,"children":[{"props":{"height":"300px","style":{"width":"100%"}},"children":[{"name":"ElCarouselItem","props":{"style":{"width":"100%"}},"children":[{"name":"component","props":{"is":"img","style":{"width":"100%","height":"300px"},"src":"https://fuss10.elemecdn.com/e/5d/4a731a90594a4af544c0c25941171jpeg.jpeg"},"id":"n22888sorj","from":"","invisible":false,"children":"","directives":[],"events":{}}],"directives":[{"id":"1igtlzxfr6o","name":"vFor","value":{"type":"JSExpression","value":"3"}}],"id":"b55hwi2k4f","from":"","invisible":false,"events":{}}],"name":"ElCarousel","from":"element-plus","id":"1yt8rgxia1r","invisible":false,"directives":[],"events":{}},{"name":"ElInput","from":"element-plus","id":"1emkugz21w2","invisible":false,"slot":{"name":"footer","params":[]},"children":"","props":{},"directives":[],"events":{}}],"directives":[],"events":{}}]}},{"id":"171mxcrvgoz","title":"2023/9/28 09:28:08","block":{"name":"MyBlock","title":"测试区块","inject":[],"state":{},"lifeCycles":{},"methods":{},"computed":{},"watch":[],"css":"","props":[{"name":"title","type":["String"],"required":false,"default":{"type":"JSExpression","value":"'默认参数标题文本'"}}],"emits":["submit"],"slots":[],"transform":{},"dataSources":{},"__VTJ_BLOCK__":true,"id":"1bh5ci0vpnp","children":[{"props":{"header":{"type":"JSExpression","value":"this.$props.title"}},"name":"XPanel","from":"@vtj/ui","id":"1e4ussdvwj4","invisible":false,"children":[{"props":{"height":"300px","style":{"width":"100%"}},"children":[{"name":"ElCarouselItem","props":{"style":{"width":"100%"}},"children":[{"name":"component","props":{"is":"img","style":{"width":"100%","height":"300px"},"src":"https://fuss10.elemecdn.com/e/5d/4a731a90594a4af544c0c25941171jpeg.jpeg"},"id":"n22888sorj","from":"","invisible":false,"children":"","directives":[],"events":{}}],"directives":[{"id":"1igtlzxfr6o","name":"vFor","value":{"type":"JSExpression","value":"3"}}],"id":"b55hwi2k4f","from":"","invisible":false,"events":{}}],"name":"ElCarousel","from":"element-plus","id":"1yt8rgxia1r","invisible":false,"directives":[],"events":{}},{"name":"ElButton","children":"测试触发事件","props":{"type":"primary"},"from":"element-plus","id":"ix6mw4vvx6","invisible":false,"slot":{"name":"footer","params":[]},"directives":[],"events":{}},{"name":"ElInput","from":"element-plus","id":"1emkugz21w2","invisible":false,"slot":{"name":"footer","params":[]},"children":"","props":{},"directives":[],"events":{}}],"directives":[],"events":{}}]}},{"id":"2qdrdpnrv3y","title":"2023/9/28 09:28:08","block":{"name":"MyBlock","title":"测试区块","inject":[],"state":{},"lifeCycles":{},"methods":{},"computed":{},"watch":[],"css":"","props":[{"name":"title","type":["String"],"required":false,"default":{"type":"JSExpression","value":"'默认参数标题文本'"}}],"emits":["submit"],"slots":[],"transform":{},"dataSources":{},"__VTJ_BLOCK__":true,"id":"1bh5ci0vpnp","children":[{"props":{"header":{"type":"JSExpression","value":"this.$props.title"}},"name":"XPanel","from":"@vtj/ui","id":"1e4ussdvwj4","invisible":false,"children":[{"props":{"height":"300px","style":{"width":"100%"}},"children":[{"name":"ElCarouselItem","props":{"style":{"width":"100%"}},"children":[{"name":"component","props":{"is":"img","style":{"width":"100%","height":"300px"},"src":"https://fuss10.elemecdn.com/e/5d/4a731a90594a4af544c0c25941171jpeg.jpeg"},"id":"n22888sorj","from":"","invisible":false,"children":"","directives":[],"events":{}}],"directives":[{"id":"1igtlzxfr6o","name":"vFor","value":{"type":"JSExpression","value":"3"}}],"id":"b55hwi2k4f","from":"","invisible":false,"events":{}}],"name":"ElCarousel","from":"element-plus","id":"1yt8rgxia1r","invisible":false,"directives":[],"events":{}},{"name":"ElButton","children":"测试触发事件","props":{"type":"primary"},"from":"element-plus","id":"ix6mw4vvx6","invisible":false,"slot":{"name":"footer","params":[]},"directives":[],"events":{}}],"directives":[],"events":{}}]}},{"id":"2n4s9t045k8","title":"2023/9/28 09:27:57","block":{"name":"MyBlock","title":"测试区块","inject":[],"state":{},"lifeCycles":{},"methods":{},"computed":{},"watch":[],"css":"","props":[{"name":"title","type":["String"],"required":false,"default":{"type":"JSExpression","value":"'默认参数标题文本'"}}],"emits":["submit"],"slots":[],"transform":{},"dataSources":{},"__VTJ_BLOCK__":true,"id":"1bh5ci0vpnp","children":[{"props":{"header":{"type":"JSExpression","value":"this.$props.title"}},"name":"XPanel","from":"@vtj/ui","id":"1e4ussdvwj4","invisible":false,"children":[{"props":{"height":"300px","style":{"width":"100%"}},"children":[{"name":"ElCarouselItem","props":{"style":{"width":"100%"}},"children":[{"name":"component","props":{"is":"img","style":{"width":"100%","height":"300px"},"src":"https://fuss10.elemecdn.com/e/5d/4a731a90594a4af544c0c25941171jpeg.jpeg"},"id":"n22888sorj","from":"","invisible":false,"children":"","directives":[],"events":{}}],"directives":[{"id":"1igtlzxfr6o","name":"vFor","value":{"type":"JSExpression","value":"3"}}],"id":"b55hwi2k4f","from":"","invisible":false,"events":{}}],"name":"ElCarousel","from":"element-plus","id":"1yt8rgxia1r","invisible":false,"directives":[],"events":{}},{"name":"ElButton","children":"测试触发事件","props":{"type":"primary"},"from":"element-plus","id":"ix6mw4vvx6","invisible":false,"slot":{"name":"footer","params":[]},"directives":[],"events":{}}],"directives":[],"events":{}},{"name":"ElInput","from":"element-plus","id":"1emkugz21w2","invisible":false,"children":"","props":{},"directives":[],"events":{}}]}},{"id":"4n7a36tzcp","title":"2023/9/28 09:26:32","block":{"name":"MyBlock","title":"测试区块","inject":[],"state":{},"lifeCycles":{},"methods":{},"computed":{},"watch":[],"css":"","props":[{"name":"title","type":["String"],"required":false,"default":{"type":"JSExpression","value":"'默认参数标题文本'"}}],"emits":["submit"],"slots":[],"transform":{},"dataSources":{},"__VTJ_BLOCK__":true,"id":"1bh5ci0vpnp","children":[{"props":{"header":{"type":"JSExpression","value":"this.$props.title"}},"name":"XPanel","from":"@vtj/ui","id":"1e4ussdvwj4","invisible":false,"children":[{"props":{"height":"300px","style":{"width":"100%"}},"children":[{"name":"ElCarouselItem","props":{"style":{"width":"100%"}},"children":[{"name":"component","props":{"is":"img","style":{"width":"100%","height":"300px"},"src":"https://fuss10.elemecdn.com/e/5d/4a731a90594a4af544c0c25941171jpeg.jpeg"},"id":"n22888sorj","from":"","invisible":false,"children":"","directives":[],"events":{}}],"directives":[{"id":"1igtlzxfr6o","name":"vFor","value":{"type":"JSExpression","value":"3"}}],"id":"b55hwi2k4f","from":"","invisible":false,"events":{}}],"name":"ElCarousel","from":"element-plus","id":"1yt8rgxia1r","invisible":false,"directives":[],"events":{}},{"name":"ElButton","children":"测试触发事件","props":{"type":"primary"},"from":"element-plus","id":"ix6mw4vvx6","invisible":false,"slot":{"name":"footer","params":[]},"directives":[],"events":{}}],"directives":[],"events":{}}]}},{"id":"2cslagq8xmf","title":"2023/9/28 09:26:10","block":{"name":"MyBlock","title":"测试区块","inject":[],"state":{},"lifeCycles":{},"methods":{},"computed":{},"watch":[],"css":"","props":[{"name":"title","type":["String"],"required":false,"default":{"type":"JSExpression","value":"'默认参数标题文本'"}}],"emits":[],"slots":[],"transform":{},"dataSources":{},"__VTJ_BLOCK__":true,"id":"1bh5ci0vpnp","children":[{"props":{"header":{"type":"JSExpression","value":"this.$props.title"}},"name":"XPanel","from":"@vtj/ui","id":"1e4ussdvwj4","invisible":false,"children":[{"props":{"height":"300px","style":{"width":"100%"}},"children":[{"name":"ElCarouselItem","props":{"style":{"width":"100%"}},"children":[{"name":"component","props":{"is":"img","style":{"width":"100%","height":"300px"},"src":"https://fuss10.elemecdn.com/e/5d/4a731a90594a4af544c0c25941171jpeg.jpeg"},"id":"n22888sorj","from":"","invisible":false,"children":"","directives":[],"events":{}}],"directives":[{"id":"1igtlzxfr6o","name":"vFor","value":{"type":"JSExpression","value":"3"}}],"id":"b55hwi2k4f","from":"","invisible":false,"events":{}}],"name":"ElCarousel","from":"element-plus","id":"1yt8rgxia1r","invisible":false,"directives":[],"events":{}},{"name":"ElButton","children":"测试触发事件","props":{"type":"primary"},"from":"element-plus","id":"ix6mw4vvx6","invisible":false,"slot":{"name":"footer","params":[]},"directives":[],"events":{}}],"directives":[],"events":{}}]}},{"id":"1oh1s4nr04h","title":"2023/9/28 09:25:56","block":{"name":"MyBlock","title":"测试区块","inject":[],"state":{},"lifeCycles":{},"methods":{},"computed":{},"watch":[],"css":"","props":[{"name":"title","type":["String"],"required":false,"default":{"type":"JSExpression","value":"'默认参数标题文本'"}}],"emits":[],"slots":[],"transform":{},"dataSources":{},"__VTJ_BLOCK__":true,"id":"1bh5ci0vpnp","children":[{"props":{"header":"面板标题"},"name":"XPanel","from":"@vtj/ui","id":"1e4ussdvwj4","invisible":false,"children":[{"props":{"height":"300px","style":{"width":"100%"}},"children":[{"name":"ElCarouselItem","props":{"style":{"width":"100%"}},"children":[{"name":"component","props":{"is":"img","style":{"width":"100%","height":"300px"},"src":"https://fuss10.elemecdn.com/e/5d/4a731a90594a4af544c0c25941171jpeg.jpeg"},"id":"n22888sorj","from":"","invisible":false,"children":"","directives":[],"events":{}}],"directives":[{"id":"1igtlzxfr6o","name":"vFor","value":{"type":"JSExpression","value":"3"}}],"id":"b55hwi2k4f","from":"","invisible":false,"events":{}}],"name":"ElCarousel","from":"element-plus","id":"1yt8rgxia1r","invisible":false,"directives":[],"events":{}},{"name":"ElButton","children":"测试触发事件","props":{"type":"primary"},"from":"element-plus","id":"ix6mw4vvx6","invisible":false,"slot":{"name":"footer","params":[]},"directives":[],"events":{}}],"directives":[],"events":{}}]}},{"id":"1h6qotlypgq","title":"2023/9/28 09:25:23","block":{"name":"MyBlock","title":"测试区块","inject":[],"state":{},"lifeCycles":{},"methods":{},"computed":{},"watch":[],"css":"","props":[],"emits":[],"slots":[],"transform":{},"dataSources":{},"__VTJ_BLOCK__":true,"id":"1bh5ci0vpnp","children":[{"props":{"header":"面板标题"},"name":"XPanel","from":"@vtj/ui","id":"1e4ussdvwj4","invisible":false,"children":[{"props":{"height":"300px","style":{"width":"100%"}},"children":[{"name":"ElCarouselItem","props":{"style":{"width":"100%"}},"children":[{"name":"component","props":{"is":"img","style":{"width":"100%","height":"300px"},"src":"https://fuss10.elemecdn.com/e/5d/4a731a90594a4af544c0c25941171jpeg.jpeg"},"id":"n22888sorj","from":"","invisible":false,"children":"","directives":[],"events":{}}],"directives":[{"id":"1igtlzxfr6o","name":"vFor","value":{"type":"JSExpression","value":"3"}}],"id":"b55hwi2k4f","from":"","invisible":false,"events":{}}],"name":"ElCarousel","from":"element-plus","id":"1yt8rgxia1r","invisible":false,"directives":[],"events":{}},{"name":"ElButton","children":"测试触发事件","props":{"type":"primary"},"from":"element-plus","id":"ix6mw4vvx6","invisible":false,"slot":{"name":"footer","params":[]},"directives":[],"events":{}}],"directives":[],"events":{}}]}},{"id":"1bvbs8wc8o1","title":"2023/9/28 09:25:05","block":{"name":"MyBlock","title":"测试区块","inject":[],"state":{},"lifeCycles":{},"methods":{},"computed":{},"watch":[],"css":"","props":[],"emits":[],"slots":[],"transform":{},"dataSources":{},"__VTJ_BLOCK__":true,"id":"1bh5ci0vpnp","children":[{"props":{"header":"面板标题"},"name":"XPanel","from":"@vtj/ui","id":"1e4ussdvwj4","invisible":false,"children":[{"props":{"height":"300px","style":{"width":"100%"}},"children":[{"name":"ElCarouselItem","props":{"style":{"width":"100%"}},"children":[{"name":"component","props":{"is":"img","style":{"width":"100%","height":"300px"},"src":"https://fuss10.elemecdn.com/e/5d/4a731a90594a4af544c0c25941171jpeg.jpeg"},"id":"n22888sorj","from":"","invisible":false,"children":"","directives":[],"events":{}}],"directives":[{"id":"1igtlzxfr6o","name":"vFor","value":{"type":"JSExpression","value":"3"}}],"id":"b55hwi2k4f","from":"","invisible":false,"events":{}}],"name":"ElCarousel","from":"element-plus","id":"1yt8rgxia1r","invisible":false,"directives":[],"events":{}},{"name":"ElButton","children":"按钮","props":{"type":"primary"},"from":"element-plus","id":"ix6mw4vvx6","invisible":false,"slot":{"name":"footer","params":[]},"directives":[],"events":{}}],"directives":[],"events":{}}]}},{"id":"rahfi2jh0d","title":"2023/9/28 09:25:05","block":{"name":"MyBlock","title":"测试区块","inject":[],"state":{},"lifeCycles":{},"methods":{},"computed":{},"watch":[],"css":"","props":[],"emits":[],"slots":[],"transform":{},"dataSources":{},"__VTJ_BLOCK__":true,"id":"1bh5ci0vpnp","children":[{"props":{"header":"面板标题"},"name":"XPanel","from":"@vtj/ui","id":"1e4ussdvwj4","invisible":false,"children":[{"props":{"height":"300px","style":{"width":"100%"}},"children":[{"name":"ElCarouselItem","props":{"style":{"width":"100%"}},"children":[{"name":"component","props":{"is":"img","style":{"width":"100%","height":"300px"},"src":"https://fuss10.elemecdn.com/e/5d/4a731a90594a4af544c0c25941171jpeg.jpeg"},"id":"n22888sorj","from":"","invisible":false,"children":"","directives":[],"events":{}}],"directives":[{"id":"1igtlzxfr6o","name":"vFor","value":{"type":"JSExpression","value":"3"}}],"id":"b55hwi2k4f","from":"","invisible":false,"events":{}}],"name":"ElCarousel","from":"element-plus","id":"1yt8rgxia1r","invisible":false,"directives":[],"events":{}}],"directives":[],"events":{}}]}},{"id":"1mi5lebk7sb","title":"2023/9/28 09:24:57","block":{"name":"MyBlock","title":"测试区块","inject":[],"state":{},"lifeCycles":{},"methods":{},"computed":{},"watch":[],"css":"","props":[],"emits":[],"slots":[],"transform":{},"dataSources":{},"__VTJ_BLOCK__":true,"id":"1bh5ci0vpnp","children":[{"props":{"header":"面板标题"},"name":"XPanel","from":"@vtj/ui","id":"1e4ussdvwj4","invisible":false,"children":[{"props":{"height":"300px","style":{"width":"100%"}},"children":[{"name":"ElCarouselItem","props":{"style":{"width":"100%"}},"children":[{"name":"component","props":{"is":"img","style":{"width":"100%","height":"300px"},"src":"https://fuss10.elemecdn.com/e/5d/4a731a90594a4af544c0c25941171jpeg.jpeg"},"id":"n22888sorj","from":"","invisible":false,"children":"","directives":[],"events":{}}],"directives":[{"id":"1igtlzxfr6o","name":"vFor","value":{"type":"JSExpression","value":"3"}}],"id":"b55hwi2k4f","from":"","invisible":false,"events":{}}],"name":"ElCarousel","from":"element-plus","id":"1yt8rgxia1r","invisible":false,"directives":[],"events":{}}],"directives":[],"events":{}},{"name":"ElButton","children":"按钮","props":{"type":"primary"},"from":"element-plus","id":"ix6mw4vvx6","invisible":false,"directives":[],"events":{}}]}},{"id":"51dpu1zx3k","title":"2023/9/28 09:24:41","block":{"name":"MyBlock","title":"测试区块","inject":[],"state":{},"lifeCycles":{},"methods":{},"computed":{},"watch":[],"css":"","props":[],"emits":[],"slots":[],"transform":{},"dataSources":{},"__VTJ_BLOCK__":true,"id":"1bh5ci0vpnp","children":[{"props":{"header":"面板标题"},"name":"XPanel","from":"@vtj/ui","id":"1e4ussdvwj4","invisible":false,"children":[{"props":{"height":"300px","style":{"width":"100%"}},"children":[{"name":"ElCarouselItem","props":{"style":{"width":"100%"}},"children":[{"name":"component","props":{"is":"img","style":{"width":"100%","height":"300px"},"src":"https://fuss10.elemecdn.com/e/5d/4a731a90594a4af544c0c25941171jpeg.jpeg"},"id":"n22888sorj","from":"","invisible":false,"children":"","directives":[],"events":{}}],"directives":[{"id":"1igtlzxfr6o","name":"vFor","value":{"type":"JSExpression","value":"3"}}],"id":"b55hwi2k4f","from":"","invisible":false,"events":{}}],"name":"ElCarousel","from":"element-plus","id":"1yt8rgxia1r","invisible":false,"directives":[],"events":{}}],"directives":[],"events":{}}]}},{"id":"2c3s0wpixkm","title":"2023/9/28 09:24:15","block":{"name":"MyBlock","title":"测试区块","inject":[],"state":{},"lifeCycles":{},"methods":{},"computed":{},"watch":[],"css":"","props":[],"emits":[],"slots":[],"transform":{},"dataSources":{},"__VTJ_BLOCK__":true,"id":"1bh5ci0vpnp","children":[{"props":{"header":"面板标题"},"name":"XPanel","from":"@vtj/ui","id":"1e4ussdvwj4","invisible":false,"children":"","directives":[],"events":{}}]}},{"id":"xhsti8dzks","title":"2023/9/28 09:24:07","block":{"name":"MyBlock","title":"测试区块","inject":[],"state":{},"lifeCycles":{},"methods":{},"computed":{},"watch":[],"css":"","props":[],"emits":[],"slots":[],"transform":{},"dataSources":{},"__VTJ_BLOCK__":true,"id":"1bh5ci0vpnp","children":[]}},{"id":"acsmerl9av","title":"2023/9/28 09:24:07","block":{"name":"MyBlock","title":"测试区块","inject":[],"state":{},"lifeCycles":{},"methods":{},"computed":{},"watch":[],"css":"","props":[],"emits":[],"slots":[],"transform":{},"dataSources":{},"__VTJ_BLOCK__":true,"id":"1bh5ci0vpnp","children":[{"name":"ElButtonGroup","children":[{"name":"ElButton","children":"Button2","id":"2dvkzrlvdp7","from":"","invisible":false,"props":{},"directives":[],"events":{}}],"from":"element-plus","id":"2cp1oj06h3u","invisible":false,"props":{},"directives":[],"events":{}}]}},{"id":"auio3cmmvn","title":"2023/9/28 09:24:07","block":{"name":"MyBlock","title":"测试区块","inject":[],"state":{},"lifeCycles":{},"methods":{},"computed":{},"watch":[],"css":"","props":[],"emits":[],"slots":[],"transform":{},"dataSources":{},"__VTJ_BLOCK__":true,"id":"1bh5ci0vpnp","children":[{"name":"ElButtonGroup","children":[{"name":"ElButton","children":"Button2","id":"2dvkzrlvdp7","from":"","invisible":false,"props":{},"directives":[],"events":{}},{"name":"ElButton","children":"Button3","id":"24x0jjddijf","from":"","invisible":false,"props":{},"directives":[],"events":{}}],"from":"element-plus","id":"2cp1oj06h3u","invisible":false,"props":{},"directives":[],"events":{}}]}},{"id":"1slxdgrls6l","title":"2023/9/28 09:24:05","block":{"name":"MyBlock","title":"测试区块","inject":[],"state":{},"lifeCycles":{},"methods":{},"computed":{},"watch":[],"css":"","props":[],"emits":[],"slots":[],"transform":{},"dataSources":{},"__VTJ_BLOCK__":true,"id":"1bh5ci0vpnp","children":[{"name":"ElButtonGroup","children":[{"name":"ElButton","children":"Button1","id":"1d1v3hht5wb","from":"","invisible":false,"props":{},"directives":[],"events":{}},{"name":"ElButton","children":"Button2","id":"2dvkzrlvdp7","from":"","invisible":false,"props":{},"directives":[],"events":{}},{"name":"ElButton","children":"Button3","id":"24x0jjddijf","from":"","invisible":false,"props":{},"directives":[],"events":{}}],"from":"element-plus","id":"2cp1oj06h3u","invisible":false,"props":{},"directives":[],"events":{}}]}},{"id":"130axydm5zw","title":"2023/9/28 09:24:05","block":{"name":"MyBlock","title":"测试区块","inject":[],"state":{},"lifeCycles":{},"methods":{},"computed":{},"watch":[],"css":"","props":[],"emits":[],"slots":[],"transform":{},"dataSources":{},"__VTJ_BLOCK__":true,"id":"1bh5ci0vpnp","children":[{"props":{"height":"300px","style":{"width":"100%"}},"children":[],"name":"ElCarousel","from":"element-plus","id":"2ot1mq6in74","invisible":false,"directives":[],"events":{}},{"name":"ElButtonGroup","children":[{"name":"ElButton","children":"Button1","id":"1d1v3hht5wb","from":"","invisible":false,"props":{},"directives":[],"events":{}},{"name":"ElButton","children":"Button2","id":"2dvkzrlvdp7","from":"","invisible":false,"props":{},"directives":[],"events":{}},{"name":"ElButton","children":"Button3","id":"24x0jjddijf","from":"","invisible":false,"props":{},"directives":[],"events":{}}],"from":"element-plus","id":"2cp1oj06h3u","invisible":false,"props":{},"directives":[],"events":{}}]}},{"id":"14okavkcg61","title":"2023/9/28 09:24:05","block":{"name":"MyBlock","title":"测试区块","inject":[],"state":{},"lifeCycles":{},"methods":{},"computed":{},"watch":[],"css":"","props":[],"emits":[],"slots":[],"transform":{},"dataSources":{},"__VTJ_BLOCK__":true,"id":"1bh5ci0vpnp","children":[{"props":{"height":"300px","style":{"width":"100%"}},"children":[{"name":"ElCarouselItem","props":{"style":{"width":"100%"}},"children":[{"name":"component","props":{"is":"img","style":{"width":"100%","height":"300px"},"src":"https://fuss10.elemecdn.com/e/5d/4a731a90594a4af544c0c25941171jpeg.jpeg"},"id":"1hogqi6rlkf","from":"","invisible":false,"children":"","directives":[],"events":{}}],"directives":[{"id":"oxet0uxkhb","name":"vFor","value":{"type":"JSExpression","value":"3"}}],"id":"lz2ixcpazz","from":"","invisible":false,"events":{}}],"name":"ElCarousel","from":"element-plus","id":"2ot1mq6in74","invisible":false,"directives":[],"events":{}},{"name":"ElButtonGroup","children":[{"name":"ElButton","children":"Button1","id":"1d1v3hht5wb","from":"","invisible":false,"props":{},"directives":[],"events":{}},{"name":"ElButton","children":"Button2","id":"2dvkzrlvdp7","from":"","invisible":false,"props":{},"directives":[],"events":{}},{"name":"ElButton","children":"Button3","id":"24x0jjddijf","from":"","invisible":false,"props":{},"directives":[],"events":{}}],"from":"element-plus","id":"2cp1oj06h3u","invisible":false,"props":{},"directives":[],"events":{}}]}},{"id":"1vgq1mk0boe","title":"2023/9/28 09:23:35","block":{"name":"MyBlock","title":"测试区块","inject":[],"state":{},"lifeCycles":{},"methods":{},"computed":{},"watch":[],"css":"","props":[],"emits":[],"slots":[],"transform":{},"dataSources":{},"__VTJ_BLOCK__":true,"id":"1bh5ci0vpnp","children":[{"props":{"height":"300px","style":{"width":"100%"}},"children":[{"name":"ElCarouselItem","props":{"style":{"width":"100%"}},"children":[{"props":{"content":"标题文本内容"},"name":"XHeader","from":"@vtj/ui","id":"wet47chgrd","invisible":false,"children":"","directives":[],"events":{}},{"name":"component","props":{"is":"img","style":{"width":"100%","height":"300px"},"src":"https://fuss10.elemecdn.com/e/5d/4a731a90594a4af544c0c25941171jpeg.jpeg"},"id":"1hogqi6rlkf","from":"","invisible":false,"children":"","directives":[],"events":{}}],"directives":[{"id":"oxet0uxkhb","name":"vFor","value":{"type":"JSExpression","value":"3"}}],"id":"lz2ixcpazz","from":"","invisible":false,"events":{}}],"name":"ElCarousel","from":"element-plus","id":"2ot1mq6in74","invisible":false,"directives":[],"events":{}},{"name":"ElButtonGroup","children":[{"name":"ElButton","children":"Button1","id":"1d1v3hht5wb","from":"","invisible":false,"props":{},"directives":[],"events":{}},{"name":"ElButton","children":"Button2","id":"2dvkzrlvdp7","from":"","invisible":false,"props":{},"directives":[],"events":{}},{"name":"ElButton","children":"Button3","id":"24x0jjddijf","from":"","invisible":false,"props":{},"directives":[],"events":{}}],"from":"element-plus","id":"2cp1oj06h3u","invisible":false,"props":{},"directives":[],"events":{}}]}},{"id":"x75zp2s0mh","title":"2023/9/28 09:18:52","block":{"name":"MyBlock","title":"测试区块","inject":[],"state":{},"lifeCycles":{},"methods":{},"computed":{},"watch":[],"css":"","props":[],"emits":[],"slots":[],"transform":{},"dataSources":{},"__VTJ_BLOCK__":true,"id":"1bh5ci0vpnp","children":[{"props":{"height":"300px","style":{"width":"100%"}},"children":[{"name":"ElCarouselItem","props":{"style":{"width":"100%"}},"children":[{"name":"component","props":{"is":"img","style":{"width":"100%","height":"300px"},"src":"https://fuss10.elemecdn.com/e/5d/4a731a90594a4af544c0c25941171jpeg.jpeg"},"id":"1hogqi6rlkf","from":"","invisible":false,"children":"","directives":[],"events":{}}],"directives":[{"id":"oxet0uxkhb","name":"vFor","value":{"type":"JSExpression","value":"3"}}],"id":"lz2ixcpazz","from":"","invisible":false,"events":{}}],"name":"ElCarousel","from":"element-plus","id":"2ot1mq6in74","invisible":false,"directives":[],"events":{}},{"name":"ElButtonGroup","children":[{"name":"ElButton","children":"Button1","id":"1d1v3hht5wb","from":"","invisible":false,"props":{},"directives":[],"events":{}},{"name":"ElButton","children":"Button2","id":"2dvkzrlvdp7","from":"","invisible":false,"props":{},"directives":[],"events":{}},{"name":"ElButton","children":"Button3","id":"24x0jjddijf","from":"","invisible":false,"props":{},"directives":[],"events":{}}],"from":"element-plus","id":"2cp1oj06h3u","invisible":false,"props":{},"directives":[],"events":{}}]}},{"id":"1selxe4u80","title":"2023/9/28 09:18:47","block":{"name":"MyBlock","title":"测试区块","inject":[],"state":{},"lifeCycles":{},"methods":{},"computed":{},"watch":[],"css":"","props":[],"emits":[],"slots":[],"transform":{},"dataSources":{},"__VTJ_BLOCK__":true,"id":"1bh5ci0vpnp","children":[{"props":{"height":"300px","style":{"width":"100%"}},"children":[{"name":"ElCarouselItem","props":{"style":{"width":"100%"}},"children":[{"name":"component","props":{"is":"img","style":{"width":"100%","height":"300px"},"src":"https://fuss10.elemecdn.com/e/5d/4a731a90594a4af544c0c25941171jpeg.jpeg"},"id":"1hogqi6rlkf","from":"","invisible":false,"children":"","directives":[],"events":{}}],"directives":[{"id":"oxet0uxkhb","name":"vFor","value":{"type":"JSExpression","value":"3"}}],"id":"lz2ixcpazz","from":"","invisible":false,"events":{}}],"name":"ElCarousel","from":"element-plus","id":"2ot1mq6in74","invisible":false,"directives":[],"events":{}}]}}]
